backend_client/__init__.py
backend_client/py.typed
backend_client/client/__init__.py
backend_client/client/api_client.py
backend_client/models/__init__.py
backend_client/models/ai.py
backend_client/models/telegram.py
backend_client/models/user.py
backend_client/models/vacancy.py
linkedin_backend_api-0.2.12.dist-info/METADATA
linkedin_backend_api-0.2.12.dist-info/WHEEL
linkedin_backend_api-0.2.12.dist-info/top_level.txt
linkedin_backend_api-0.2.12.dist-info/RECORD
