Metadata-Version: 2.4
Name: linkedin-backend-api
Version: 0.2.12
Summary: Add your description here
Home-page: https://github.com/0x216/linkedin-backend-api
Author: 
Author-email: example@example.com
Requires-Python: >=3.8
Requires-Dist: aiohttp==3.11.18
Requires-Dist: pydantic==2.11.3
Dynamic: author-email
Dynamic: home-page
Dynamic: requires-python
